quickgraph/__init__.py
quickgraph/links_16007.csv
quickgraph/nodes_16007.csv
quickgraph/quickgraph.py
quickgraph-0.45.dist-info/LICENSE
quickgraph-0.45.dist-info/METADATA
quickgraph-0.45.dist-info/WHEEL
quickgraph-0.45.dist-info/top_level.txt
quickgraph-0.45.dist-info/RECORD
