Metadata-Version: 2.1
Name: quickgraph
Version: 0.45
Summary: A Python package to view the skeleton of a social graph quickly.
Home-page: https://gongqingyuan.wordpress.com/
Author: Mobile Systems and Networking Group, Fudan University
Author-email: gongqingyuan@fudan.edu.cn
License: UNKNOWN
Platform: UNKNOWN
Classifier: Programming Language :: Python :: 3
Classifier: License :: OSI Approved :: MIT License
Classifier: Operating System :: OS Independent
Classifier: Intended Audience :: Science/Research
Classifier: Topic :: Scientific/Engineering
License-File: LICENSE
